pyReqCheck/__init__.py
pyReqCheck/__main__.py
pyReqCheck/mapping
pyReqCheck/pyReqCheck.py
pyReqCheck/stdlib
pyReqCheck-0.991.dist-info/LICENSE
pyReqCheck-0.991.dist-info/METADATA
pyReqCheck-0.991.dist-info/WHEEL
pyReqCheck-0.991.dist-info/top_level.txt
pyReqCheck-0.991.dist-info/RECORD
