Metadata-Version: 2.1
Name: pyReqCheck
Version: 0.991
Summary: Python library for checking if any modules are missing in your project's requirements.txt file
Author-email: Joar Gjersund <joargjersund@gmail.com>
Project-URL: Homepage, https://github.com/JoarGjersund/pyReqCheck
Project-URL: Issues, https://github.com/JoarGjersund/pyReqCheck/issues
Classifier: Programming Language :: Python :: 3
Classifier: License :: OSI Approved :: MIT License
Classifier: Operating System :: OS Independent
Requires-Python: >=3.8
License-File: LICENSE
